fpfs/__init__.py
fpfs/__version__.py
fpfs/catalog.py
fpfs/default.py
fpfs/image.py
fpfs/imgutil.py
fpfs/io.py
fpfs/pltutil.py
fpfs/simutil.py
fpfs/tasks.py
fpfs/data/correlation.fits
fpfs/data/fpfs-cut32-0000-g1-0000.fits
fpfs/data/noiPows3.npy
fpfs/data/src_cosmos.fits
fpfs-3.1.1.data/scripts/fpfs_config
fpfs-3.1.1.data/scripts/fpfs_process_descsim.py
fpfs-3.1.1.data/scripts/fpfs_process_sim.py
fpfs-3.1.1.data/scripts/fpfs_sim.py
fpfs-3.1.1.data/scripts/fpfs_summary_descsim.py
fpfs-3.1.1.data/scripts/fpfs_summary_sim.py
fpfs-3.1.1.dist-info/LICENSE
fpfs-3.1.1.dist-info/METADATA
fpfs-3.1.1.dist-info/WHEEL
fpfs-3.1.1.dist-info/top_level.txt
fpfs-3.1.1.dist-info/RECORD
